gitlab_auto_version/__init__.py
gitlab_auto_version/gitlab_auto_version.py
gitlab_auto_version-1.0.6.dist-info/LICENSE
gitlab_auto_version-1.0.6.dist-info/METADATA
gitlab_auto_version-1.0.6.dist-info/WHEEL
gitlab_auto_version-1.0.6.dist-info/entry_points.txt
gitlab_auto_version-1.0.6.dist-info/top_level.txt
gitlab_auto_version-1.0.6.dist-info/RECORD
