Metadata-Version: 2.1
Name: gitlab-auto-version
Version: 1.0.6
Summary: A package to automate version bumping and Git tagging in GitLab CI.
Home-page: https://gitlab.com/mosiko1234/gitlab-auto-version
Author: Moshe Eliya
Author-email: mosiko1234@gmail.com
Classifier: Programming Language :: Python :: 3
Classifier: License :: OSI Approved :: MIT License
Classifier: Operating System :: OS Independent
Requires-Python: >=3.6
License-File: LICENSE
Requires-Dist: configparser
Requires-Dist: PyYAML
